find_aws_regions/__init__.py
find_aws_regions/test.py
find_aws_regions-0.0.3.dist-info/LICENSE
find_aws_regions-0.0.3.dist-info/METADATA
find_aws_regions-0.0.3.dist-info/WHEEL
find_aws_regions-0.0.3.dist-info/top_level.txt
find_aws_regions-0.0.3.dist-info/RECORD
