Metadata-Version: 2.1
Name: find-aws-regions
Version: 0.0.3
Summary: Find the closest/best AWS region from your code bassed on latency
Home-page: https://github.com/junderhill/py-find-aws-region
Author: Jason Underhill
Author-email: jason@junderhill.com
Classifier: Programming Language :: Python :: 3
Classifier: License :: OSI Approved :: MIT License
Classifier: Operating System :: OS Independent
Requires-Python: >=3.6
License-File: LICENSE
Requires-Dist: boto3
Requires-Dist: requests >=2.31.0
